localqtl/__init__.py
localqtl/_torch_utils.py
localqtl/cis/__init__.py
localqtl/cis/_buffer.py
localqtl/cis/_permute.py
localqtl/cis/common.py
localqtl/cis/independent.py
localqtl/cis/mapper.py
localqtl/cis/nominal.py
localqtl/cis/permutations.py
localqtl/cis/postproc.py
localqtl/finemap.py
localqtl/genotypeio.py
localqtl/haplotypeio.py
localqtl/iosinks.py
localqtl/pgen.py
localqtl/phenotypeio.py
localqtl/preproc.py
localqtl/regression_kernels.py
localqtl/stats.py
localqtl/utils.py
localqtl-0.1.3.dist-info/METADATA
localqtl-0.1.3.dist-info/WHEEL
localqtl-0.1.3.dist-info/RECORD
