Metadata-Version: 2.4
Name: localqtl
Version: 0.1.3
Summary: GPU-accelerated ancestry-aware cis-QTL mapping library with tensorQTL-compatible APIs
License: GPL-3.0-or-later
Keywords: genomics,gpu,xQTL,qtl
Author: Kynon J Benjamin
Author-email: kj.benjamin90@gmail.com
Maintainer: Kynon J Benjamin
Maintainer-email: kj.benjamin90@gmail.com
Requires-Python: >=3.11,<3.15
Classifier: License :: OSI Approved :: GNU General Public License v3 or later (GPLv3+)
Classifier: Programming Language :: Python :: 3
Classifier: Programming Language :: Python :: 3.11
Classifier: Programming Language :: Python :: 3.12
Classifier: Programming Language :: Python :: 3.13
Classifier: Programming Language :: Python :: 3.14
Requires-Dist: cudf-cu12 (>=25.10,<26.0)
Requires-Dist: cupy-cuda12x (>=13.6,<14.0)
Requires-Dist: dask-cudf-cu12 (>=25.10.0,<26.0.0)
Requires-Dist: numpy (>=2.0,<3.0)
Requires-Dist: pandas (>=2.2,<3.0)
Requires-Dist: pandas-plink-ng (>=2.3.2.post1,<3.0.0)
Requires-Dist: pgenlib (>=0.93,<0.94)
Requires-Dist: py-qvalue (>=0.1,<0.2)
Requires-Dist: pyarrow (>=22.0,<23.0)
Requires-Dist: rfmix-reader (>=0.2,<0.3)
Requires-Dist: scipy (>=1.16,<2.0)
Requires-Dist: torch (>=2.8,<3.0)
Project-URL: Bug Tracker, https://github.com/heart-gen/localQTL/issues
Project-URL: homepage, https://localqtl.readthedocs.io/en/latest/
Project-URL: repository, https://github.com/heart-gen/localQTL
